curl_loop_runner/__init__.py
curl_loop_runner/__main__.py
curl_loop_runner/_version.py
curl_loop_runner/cli.py
curl_loop_runner/gui.py
curl_loop_runner-0.1.dev4.dist-info/licenses/LICENSE
curl_loop_runner-0.1.dev4.dist-info/METADATA
curl_loop_runner-0.1.dev4.dist-info/WHEEL
curl_loop_runner-0.1.dev4.dist-info/entry_points.txt
curl_loop_runner-0.1.dev4.dist-info/top_level.txt
curl_loop_runner-0.1.dev4.dist-info/RECORD
