Metadata-Version: 2.4
Name: curl-loop-runner
Version: 0.1.dev4
Summary: A GUI application for running curl commands in a loop with configurable sleep time
Author-email: Your Name <your.email@example.com>
License: MIT
Project-URL: Homepage, https://gitlab.com/your-username/curl-loop-runner
Project-URL: Repository, https://gitlab.com/your-username/curl-loop-runner.git
Project-URL: Issues, https://gitlab.com/your-username/curl-loop-runner/-/issues
Keywords: curl,gui,http,api,testing,monitoring
Classifier: Development Status :: 4 - Beta
Classifier: Intended Audience :: Developers
Classifier: License :: OSI Approved :: MIT License
Classifier: Operating System :: OS Independent
Classifier: Programming Language :: Python :: 3
Classifier: Programming Language :: Python :: 3.7
Classifier: Programming Language :: Python :: 3.8
Classifier: Programming Language :: Python :: 3.9
Classifier: Programming Language :: Python :: 3.10
Classifier: Programming Language :: Python :: 3.11
Classifier: Programming Language :: Python :: 3.12
Classifier: Topic :: Software Development :: Testing
Classifier: Topic :: Internet :: WWW/HTTP
Requires-Python: >=3.7
License-File: LICENSE
Dynamic: license-file
